{
	"schemaVersion": 2,
	"mediaType": "application/vnd.oci.image.index.v1+json",
	"manifests": [
		{
			"mediaType": "application/vnd.oci.image.manifest.v1+json",
			"digest": "sha256:b3fa0a3d13103deb92d0763a3bf8d47635f31781d1210c2633e974213ab8e583",
			"size": 610,
			"platform": {
				"architecture": "arm",
				"os": "linux",
				"variant": "v5"
			},
			"annotations": {
				"org.opencontainers.image.ref.name": "busybox:1.37.0-uclibc",
				"io.containerd.image.name": "busybox:1.37.0-uclibc"
			}
		}
	]
}
